 
 
 
 
 
 
 
 
 
 
 
 
 
 
 
 
 
 
 
 
 
 
 
 
 
 
 
 
 
 
 
 
 
 
 
 
 
 
 
 
 
 
 
 
 
 
 
 
 
 
 
 
 
 
 
 
 
 
 
 
 
 
 
 
 
 
 
 
 
 
 
 
 
 
 
 
 
 
 
 
 
 
 
 
 
 
 
 
 
 
 
 
 
 
 
 
 
 
 
 
 
 
 
 
 
 
 
 
 
 
 
 
 
 
 
 
 
 
 
 
 
 
 
 
 
 
 
 
 
 
 
 
 
 
 
 
 
 
 
 
 
 
 
 
 
 
 
 
 
 
 
 
 
 
 
 
 
 
 
 
 
 
 
 
 
 
 
 
 
 
 
 
 
 
 
 
 
 
 
 
 
 
 
 
 
 
 
 
 
 
 
 
 
 
 
 
 
{
"corpora": {
"FAMILJELIV-ADOPTION": {
"absolute": {
"2003": 0,
"2023": null
},
"relative": {
"2003": 0,
"2023": null
},
"sums": {
"absolute": 0,
"relative": 0.0
}
},
"FAMILJELIV-ALLMANNA-EKONOMI": {
"absolute": {
"2003": 0,
"2023": null
},
"relative": {
"2003": 0,
"2023": null
},
"sums": {
"absolute": 0,
"relative": 0.0
}
},
"FAMILJELIV-ALLMANNA-FAMILJELIV": {
"absolute": {
"2003": 0,
"2023": null
},
"relative": {
"2003": 0,
"2023": null
},
"sums": {
"absolute": 0,
"relative": 0.0
}
},
"FAMILJELIV-ALLMANNA-FRITID": {
"absolute": {
"2004": 0,
"2023": null
},
"relative": {
"2004": 0,
"2023": null
},
"sums": {
"absolute": 0,
"relative": 0.0
}
},
"FAMILJELIV-ALLMANNA-HUSDJUR": {
"absolute": {
"2003": 0,
"2023": null
},
"relative": {
"2003": 0,
"2023": null
},
"sums": {
"absolute": 0,
"relative": 0.0
}
},
"FAMILJELIV-ALLMANNA-HUSHEM": {
"absolute": {
"2004": 0,
"2023": null
},
"relative": {
"2004": 0,
"2023": null
},
"sums": {
"absolute": 0,
"relative": 0.0
}
},
"FAMILJELIV-ALLMANNA-KROPP": {
"absolute": {
"2003": 0,
"2023": null
},
"relative": {
"2003": 0,
"2023": null
},
"sums": {
"absolute": 0,
"relative": 0.0
}
},
"FAMILJELIV-ALLMANNA-NOJE": {
"absolute": {
"2003": 0,
"2023": null
},
"relative": {
"2003": 0,
"2023": null
},
"sums": {
"absolute": 0,
"relative": 0.0
}
},
"FAMILJELIV-ALLMANNA-SAMHALLE": {
"absolute": {
"2003": 0,
"2022": null
},
"relative": {
"2003": 0,
"2022": null
},
"sums": {
"absolute": 0,
"relative": 0.0
}
},
"FAMILJELIV-ALLMANNA-SANDLADAN": {
"absolute": {
"2005": 0,
"2022": null
},
"relative": {
"2005": 0,
"2022": null
},
"sums": {
"absolute": 0,
"relative": 0.0
}
},
"FAMILJELIV-ANGLARUM": {
"absolute": {
"2006": 0,
"2022": null
},
"relative": {
"2006": 0,
"2022": null
},
"sums": {
"absolute": 0,
"relative": 0.0
}
},
"FAMILJELIV-EXPERT": {
"absolute": {
"2009": 0,
"2023": null
},
"relative": {
"2009": 0,
"2023": null
},
"sums": {
"absolute": 0,
"relative": 0.0
}
},
"FAMILJELIV-FORALDER": {
"absolute": {
"2003": 0,
"2022": null
},
"relative": {
"2003": 0,
"2022": null
},
"sums": {
"absolute": 0,
"relative": 0.0
}
},
"FAMILJELIV-GRAVID": {
"absolute": {
"2003": 0,
"2022": null,
"2007": 2,
"2008": 0,
"2011": 1,
"2012": 2,
"2013": 1,
"2014": 0
},
"relative": {
"2003": 0,
"2022": null,
"2007": 0.04146970457687445,
"2008": 0.0,
"2011": 0.021719441289092277,
"2012": 0.048473740066306746,
"2013": 0.03644591799340438,
"2014": 0.0
},
"sums": {
"absolute": 6,
"relative": 0.14810880392567785
}
},
"FAMILJELIV-KANSLIGA": {
"absolute": {
"2003": 0,
"2022": null
},
"relative": {
"2003": 0,
"2022": null
},
"sums": {
"absolute": 0,
"relative": 0.0
}
},
"FAMILJELIV-MEDLEM-ALLMANNA": {
"absolute": {
"2006": 0,
"2022": null
},
"relative": {
"2006": 0,
"2022": null
},
"sums": {
"absolute": 0,
"relative": 0.0
}
},
"FAMILJELIV-MEDLEM-FORALDRAR": {
"absolute": {
"2006": 0,
"2022": null
},
"relative": {
"2006": 0,
"2022": null
},
"sums": {
"absolute": 0,
"relative": 0.0
}
},
"FAMILJELIV-MEDLEM-PLANERARBARN": {
"absolute": {
"2005": 0,
"2021": null,
"2007": 4,
"2008": 1,
"2009": 0,
"2011": 1,
"2012": 0
},
"relative": {
"2005": 0,
"2021": null,
"2007": 0.10518652397588756,
"2008": 0.040462915171764265,
"2009": 0.0,
"2011": 0.12676141321736187,
"2012": 0.0
},
"sums": {
"absolute": 6,
"relative": 0.2724108523650137
}
},
"FAMILJELIV-MEDLEM-VANTARBARN": {
"absolute": {
"2003": 0,
"2022": null,
"2007": 1,
"2008": 0
},
"relative": {
"2003": 0,
"2022": null,
"2007": 0.017699676734874083,
"2008": 0.0
},
"sums": {
"absolute": 1,
"relative": 0.017699676734874083
}
},
"FAMILJELIV-PAPPAGRUPP": {
"absolute": {
"2004": 0,
"2023": null
},
"relative": {
"2004": 0,
"2023": null
},
"sums": {
"absolute": 0,
"relative": 0.0
}
},
"FAMILJELIV-PLANERARBARN": {
"absolute": {
"2003": 0,
"2022": null,
"2006": 1,
"2007": 0
},
"relative": {
"2003": 0,
"2022": null,
"2006": 0.04429419067515154,
"2007": 0.0
},
"sums": {
"absolute": 1,
"relative": 0.04429419067515154
}
},
"FAMILJELIV-SEXSAMLEVNAD": {
"absolute": {
"2004": 0,
"2022": null
},
"relative": {
"2004": 0,
"2022": null
},
"sums": {
"absolute": 0,
"relative": 0.0
}
},
"FAMILJELIV-SVARTATTFABARN": {
"absolute": {
"2003": 0,
"2022": null,
"2004": 1,
"2005": 8,
"2006": 5,
"2007": 2,
"2008": 1,
"2009": 4,
"2010": 1,
"2011": 2,
"2012": 3,
"2013": 0
},
"relative": {
"2003": 0,
"2022": null,
"2004": 0.19451256706793313,
"2005": 0.707865375331458,
"2006": 0.24099638703036494,
"2007": 0.09863376454700076,
"2008": 0.036850422403494364,
"2009": 0.1967765831143456,
"2010": 0.0970257719855548,
"2011": 0.15049115044314376,
"2012": 0.24207915003751015,
"2013": 0.0
},
"sums": {
"absolute": 27,
"relative": 1.9652311719608055
}
}
},
"combined": {
"absolute": {
"2003": 0,
"2023": null,
"2004": 1,
"2005": 8,
"2006": 6,
"2007": 9,
"2008": 2,
"2009": 4,
"2010": 1,
"2011": 4,
"2012": 5,
"2013": 1,
"2014": 0
},
"relative": {
"2003": 0,
"2023": null,
"2004": 0.010367229560579273,
"2005": 0.03442645800675714,
"2006": 0.012789296852324477,
"2007": 0.014174121003579614,
"2008": 0.003211603147055062,
"2009": 0.00674244357408263,
"2010": 0.0024263276366824175,
"2011": 0.0110894621091613,
"2012": 0.01721526594833169,
"2013": 0.004813311385916963,
"2014": 0.0
},
"sums": {
"absolute": 41,
"relative": 0.009180561647872051
}
},
"time": 986.8628921508789
}
